jpforcioligetscode/__init__.py
jpforcioligetscode/script.py
jpforcioligetscode-0.1.0.dist-info/entry_points.txt
jpforcioligetscode-0.1.0.dist-info/WHEEL
jpforcioligetscode-0.1.0.dist-info/METADATA
jpforcioligetscode-0.1.0.dist-info/RECORD
