Metadata-Version: 2.1
Name: jpforcioligetscode
Version: 0.1.0
Summary: Print the HTTP status code for an HTTP GET
Home-page: https://gitlab.com/jpforcioli/jpforcioligetscode
License: Apache-2.0 
Keywords: requests,cli,status_code
Author: Jean-Pierre Forcioli
Author-email: jpforcioli@fortinet.com
Requires-Python: >=3.7,<4.0
Classifier: License :: Other/Proprietary License
Classifier: Programming Language :: Python :: 3
Classifier: Programming Language :: Python :: 3.7
Classifier: Programming Language :: Python :: 3.8
Classifier: Programming Language :: Python :: 3.9
Requires-Dist: requests (>=2.25.0,<3.0.0)
